{
  "platform": "youtube",
  "username": "UCX0Qk4QtPOlEwBmsbIG4vOg",
  "fullname": "리뷰야놀자",
  "channel_id": "UCX0Qk4QtPOlEwBmsbIG4vOg",
  "profile_url": "https://www.youtube.com/channel/UCX0Qk4QtPOlEwBmsbIG4vOg",
  "followers": 699000,
  "avg_views": 91095.8,
  "avg_likes": 954.4,
  "avg_comments": 117.2,
  "engagement_rate": 0.0105,
  "posts_last_30d": 0,
  "sample_size": 5,
  "brand_fit_score": 25,
  "retailer_focus": "off_topic",
  "retailer_signal": {
    "daiso_mentions": "none",
    "olive_young_mentions": "none",
    "beauty_topical_strength": "none (0건)",
    "labrang_blanc_doux_mention": false
  },
  "total_score": 52.25,
  "score_breakdown": {
    "engagement": 60,
    "brand_fit": 25,
    "consistency": 40,
    "follower_scale": 100
  },
  "grade": "D",
  "evaluated_at": "2026-05-08T10:26:33+09:00",
  "history": [],
  "score_total": 52.25,
  "score": {
    "total": 52.25,
    "breakdown": {
      "engagement": 60,
      "brand_fit": 25,
      "consistency": 40,
      "follower_scale": 100
    },
    "weights": {
      "engagement": 0.5,
      "brand_fit": 0.25,
      "consistency": 0.15,
      "follower_scale": 0.1
    }
  },
  "notes": "youtube sample: 5 items",
  "brand_fit_notes": "daiso:none / oliveyoung:none / labrang:N",
  "sample_data_evidence": {
    "channel_url": "https://www.youtube.com/channel/UCX0Qk4QtPOlEwBmsbIG4vOg"
  },
  "post_count_total": 5,
  "view_to_sub_ratio": 0.1303,
  "top_video_views": 91095.8,
  "top_post_likes": 954.4
}